./yanchaotest.py
yanchaotest-0.1.dist-info/entry_points.txt
yanchaotest-0.1.dist-info/METADATA
yanchaotest-0.1.dist-info/WHEEL
yanchaotest-0.1.dist-info/RECORD
