Metadata-Version: 1.2
Name: yanchaotest
Version: 0.1
Summary: An amazing sample package!
Home-page: http://github.com/yanchao727
License: UNKNOWN
Author: Chao Yan
Author-email: yanchao727@gmail.com
